[
    {
        "args": [
            "*a2",
            "a2",
            "a3"
        ],
        "funName": "sub_4028D4",
        "lineNum": 9
    },
    {
        "args": [
            "sub_4023D3"
        ],
        "funName": "sub_4053E0",
        "lineNum": 13
    },
    {
        "args": [
            "1"
        ],
        "funName": "sub_401667",
        "lineNum": 24
    },
    {
        "args": [
            "1"
        ],
        "funName": "sub_401667",
        "lineNum": 30
    },
    {
        "args": [
            "v5"
        ],
        "funName": "sub_401F0B",
        "lineNum": 36
    }
]