[
    {
        "args": [
            "13LL",
            "0LL",
            "sub_406DB7",
            "sub_406DE0",
            "free"
        ],
        "funName": "sub_409B01",
        "lineNum": 19
    },
    {
        "args": [
            "v3",
            "&v8"
        ],
        "funName": "sub_4094C8",
        "lineNum": 25
    },
    {
        "args": [
            "*(_DWORD *)(v4 + 44)"
        ],
        "funName": "sub_406D6D",
        "lineNum": 31
    },
    {
        "args": [
            "v3",
            "ptr"
        ],
        "funName": "sub_40A797",
        "lineNum": 34
    }
]