{
    "argument": [
        {
            "name": "a1",
            "type": "__int64",
            "original_line": "__int64 a1"
        },
        {
            "name": "a2",
            "type": "unsigned int",
            "original_line": "unsigned int a2"
        },
        {
            "name": "a3",
            "type": "__int64",
            "original_line": "__int64 a3"
        },
        {
            "name": "a4",
            "type": "__off_t",
            "original_line": "__off_t a4"
        },
        {
            "name": "a5",
            "type": "__int64",
            "original_line": "__int64 a5"
        }
    ],
    "variable": [
        {
            "name": "v5",
            "type": "__int64",
            "comment": "r12",
            "array_size": null,
            "star_count": 0,
            "rbp_offset_hex": null,
            "rbp_offset_dec": null,
            "original_line": "__int64 v5; // r12"
        },
        {
            "name": "v6",
            "type": "char *",
            "comment": "rbx",
            "array_size": null,
            "star_count": 0,
            "rbp_offset_hex": null,
            "rbp_offset_dec": null,
            "original_line": "char *v6; // rbx"
        },
        {
            "name": "v7",
            "type": "int *",
            "comment": "rax",
            "array_size": null,
            "star_count": 0,
            "rbp_offset_hex": null,
            "rbp_offset_dec": null,
            "original_line": "int *v7; // rax"
        },
        {
            "name": "result",
            "type": "__int64",
            "comment": "rax",
            "array_size": null,
            "star_count": 0,
            "rbp_offset_hex": null,
            "rbp_offset_dec": null,
            "original_line": "__int64 result; // rax"
        },
        {
            "name": "v9",
            "type": "__int64",
            "comment": "r12",
            "array_size": null,
            "star_count": 0,
            "rbp_offset_hex": null,
            "rbp_offset_dec": null,
            "original_line": "__int64 v9; // r12"
        },
        {
            "name": "v10",
            "type": "char *",
            "comment": "rbx",
            "array_size": null,
            "star_count": 0,
            "rbp_offset_hex": null,
            "rbp_offset_dec": null,
            "original_line": "char *v10; // rbx"
        },
        {
            "name": "v11",
            "type": "int *",
            "comment": "rax",
            "array_size": null,
            "star_count": 0,
            "rbp_offset_hex": null,
            "rbp_offset_dec": null,
            "original_line": "int *v11; // rax"
        },
        {
            "name": "v13",
            "type": "const char *",
            "comment": "rbx",
            "array_size": null,
            "star_count": 0,
            "rbp_offset_hex": null,
            "rbp_offset_dec": null,
            "original_line": "const char *v13; // rbx"
        },
        {
            "name": "v14",
            "type": "int *",
            "comment": "rax",
            "array_size": null,
            "star_count": 0,
            "rbp_offset_hex": null,
            "rbp_offset_dec": null,
            "original_line": "int *v14; // rax"
        },
        {
            "name": "v15",
            "type": "__int64",
            "comment": "r12",
            "array_size": null,
            "star_count": 0,
            "rbp_offset_hex": null,
            "rbp_offset_dec": null,
            "original_line": "__int64 v15; // r12"
        },
        {
            "name": "v16",
            "type": "char *",
            "comment": "rbx",
            "array_size": null,
            "star_count": 0,
            "rbp_offset_hex": null,
            "rbp_offset_dec": null,
            "original_line": "char *v16; // rbx"
        },
        {
            "name": "v17",
            "type": "int *",
            "comment": "rax",
            "array_size": null,
            "star_count": 0,
            "rbp_offset_hex": null,
            "rbp_offset_dec": null,
            "original_line": "int *v17; // rax"
        },
        {
            "name": "v18",
            "type": "__int64",
            "comment": "r12",
            "array_size": null,
            "star_count": 0,
            "rbp_offset_hex": null,
            "rbp_offset_dec": null,
            "original_line": "__int64 v18; // r12"
        },
        {
            "name": "v19",
            "type": "char *",
            "comment": "rbx",
            "array_size": null,
            "star_count": 0,
            "rbp_offset_hex": null,
            "rbp_offset_dec": null,
            "original_line": "char *v19; // rbx"
        },
        {
            "name": "v20",
            "type": "int *",
            "comment": "rax",
            "array_size": null,
            "star_count": 0,
            "rbp_offset_hex": null,
            "rbp_offset_dec": null,
            "original_line": "int *v20; // rax"
        },
        {
            "name": "v23",
            "type": "int",
            "comment": "[rsp+3Ch] [rbp-2064h]",
            "array_size": null,
            "star_count": 0,
            "rbp_offset_hex": "-2064",
            "rbp_offset_dec": -8292,
            "original_line": "int v23; // [rsp+3Ch] [rbp-2064h]"
        },
        {
            "name": "v24",
            "type": "__int64",
            "comment": "[rsp+40h] [rbp-2060h]",
            "array_size": null,
            "star_count": 0,
            "rbp_offset_hex": "-2060",
            "rbp_offset_dec": -8288,
            "original_line": "__int64 v24; // [rsp+40h] [rbp-2060h]"
        },
        {
            "name": "v25",
            "type": "__int64",
            "comment": "[rsp+40h] [rbp-2060h]",
            "array_size": null,
            "star_count": 0,
            "rbp_offset_hex": "-2060",
            "rbp_offset_dec": -8288,
            "original_line": "__int64 v25; // [rsp+40h] [rbp-2060h]"
        },
        {
            "name": "offset",
            "type": "__off_t",
            "comment": "[rsp+48h] [rbp-2058h]",
            "array_size": null,
            "star_count": 0,
            "rbp_offset_hex": "-2058",
            "rbp_offset_dec": -8280,
            "original_line": "__off_t offset; // [rsp+48h] [rbp-2058h]"
        },
        {
            "name": "n",
            "type": "size_t",
            "comment": "[rsp+50h] [rbp-2050h]",
            "array_size": null,
            "star_count": 0,
            "rbp_offset_hex": "-2050",
            "rbp_offset_dec": -8272,
            "original_line": "size_t n; // [rsp+50h] [rbp-2050h]"
        },
        {
            "name": "v28",
            "type": "_BYTE *",
            "comment": "[rsp+58h] [rbp-2048h]",
            "array_size": null,
            "star_count": 0,
            "rbp_offset_hex": "-2048",
            "rbp_offset_dec": -8264,
            "original_line": "_BYTE *v28; // [rsp+58h] [rbp-2048h]"
        },
        {
            "name": "v29",
            "type": "char",
            "comment": "[rsp+60h] [rbp-2040h] BYREF",
            "array_size": 32,
            "star_count": 0,
            "rbp_offset_hex": "-2040",
            "rbp_offset_dec": -8256,
            "original_line": "char v29[32]; // [rsp+60h] [rbp-2040h] BYREF"
        },
        {
            "name": "s",
            "type": "char",
            "comment": "[rsp+80h] [rbp-2020h] BYREF",
            "array_size": 8200,
            "star_count": 0,
            "rbp_offset_hex": "-2020",
            "rbp_offset_dec": -8224,
            "original_line": "char s[8200]; // [rsp+80h] [rbp-2020h] BYREF"
        },
        {
            "name": "v31",
            "type": "unsigned __int64",
            "comment": "[rsp+2088h] [rbp-18h]",
            "array_size": null,
            "star_count": 0,
            "rbp_offset_hex": "-18",
            "rbp_offset_dec": -24,
            "original_line": "unsigned __int64 v31; // [rsp+2088h] [rbp-18h]"
        }
    ]
}