[
    {
        "expr": "v2",
        "exprPointeeSize": 1,
        "exprPointeeType": "char *",
        "lhsPointeeSize": 1,
        "lhsType": "char *",
        "lineNum": 22,
        "offset": 0,
        "varName": "v2"
    },
    {
        "expr": "v2",
        "exprPointeeSize": 1,
        "exprPointeeType": "char *",
        "lhsPointeeSize": 1,
        "lhsType": "char *",
        "lineNum": 23,
        "offset": 0,
        "varName": "v2"
    },
    {
        "expr": "v5",
        "exprPointeeSize": 1,
        "exprPointeeType": "char *",
        "lhsPointeeSize": 1,
        "lhsType": "char *",
        "lineNum": 29,
        "offset": 0,
        "varName": "v5"
    },
    {
        "expr": "v5",
        "exprPointeeSize": 1,
        "exprPointeeType": "char *",
        "lhsPointeeSize": 1,
        "lhsType": "char *",
        "lineNum": 30,
        "offset": 0,
        "varName": "v5"
    },
    {
        "expr": "v7",
        "exprPointeeSize": 1,
        "exprPointeeType": "char *",
        "lhsPointeeSize": 1,
        "lhsType": "char *",
        "lineNum": 32,
        "offset": 0,
        "varName": "v7"
    },
    {
        "expr": "v7",
        "exprPointeeSize": 1,
        "exprPointeeType": "char *",
        "lhsPointeeSize": 1,
        "lhsType": "char *",
        "lineNum": 36,
        "offset": 0,
        "varName": "v7"
    },
    {
        "expr": "v9",
        "exprPointeeSize": 1,
        "exprPointeeType": "char *",
        "lhsPointeeSize": 1,
        "lhsType": "char *",
        "lineNum": 38,
        "offset": 0,
        "varName": "v9"
    },
    {
        "expr": "v9",
        "exprPointeeSize": 1,
        "exprPointeeType": "char *",
        "lhsPointeeSize": 1,
        "lhsType": "char *",
        "lineNum": 39,
        "offset": 0,
        "varName": "v9"
    },
    {
        "expr": "v11",
        "exprPointeeSize": 1,
        "exprPointeeType": "char *",
        "lhsPointeeSize": 1,
        "lhsType": "char *",
        "lineNum": 41,
        "offset": 0,
        "varName": "v11"
    },
    {
        "expr": "v11",
        "exprPointeeSize": 1,
        "exprPointeeType": "char *",
        "lhsPointeeSize": 1,
        "lhsType": "char *",
        "lineNum": 42,
        "offset": 0,
        "varName": "v11"
    },
    {
        "expr": "v14",
        "exprPointeeSize": 1,
        "exprPointeeType": "char *",
        "lhsPointeeSize": 1,
        "lhsType": "char *",
        "lineNum": 45,
        "offset": 0,
        "varName": "v14"
    },
    {
        "expr": "v14",
        "exprPointeeSize": 1,
        "exprPointeeType": "char *",
        "lhsPointeeSize": 1,
        "lhsType": "char *",
        "lineNum": 46,
        "offset": 0,
        "varName": "v14"
    }
]