[
    {
        "expr": "s1",
        "exprPointeeSize": 1,
        "exprPointeeType": "unsigned char *",
        "lhsPointeeSize": 1,
        "lhsType": "unsigned char *",
        "lineNum": 52,
        "offset": 0,
        "varName": "s1"
    },
    {
        "expr": "a1[2]",
        "exprPointeeSize": 8,
        "exprPointeeType": "unsigned char *",
        "lhsPointeeSize": 8,
        "lhsType": "unsigned char **",
        "lineNum": 52,
        "offset": 2,
        "varName": "a1"
    },
    {
        "expr": "s2",
        "exprPointeeSize": 1,
        "exprPointeeType": "unsigned char *",
        "lhsPointeeSize": 1,
        "lhsType": "unsigned char *",
        "lineNum": 53,
        "offset": 0,
        "varName": "s2"
    },
    {
        "expr": "a2[2]",
        "exprPointeeSize": 8,
        "exprPointeeType": "unsigned char *",
        "lhsPointeeSize": 8,
        "lhsType": "unsigned char **",
        "lineNum": 53,
        "offset": 2,
        "varName": "a2"
    },
    {
        "expr": "v29",
        "exprPointeeSize": 1,
        "exprPointeeType": "unsigned char *",
        "lhsPointeeSize": 1,
        "lhsType": "unsigned char *",
        "lineNum": 54,
        "offset": 0,
        "varName": "v29"
    },
    {
        "expr": "a1[3]",
        "exprPointeeSize": 8,
        "exprPointeeType": "unsigned char *",
        "lhsPointeeSize": 8,
        "lhsType": "unsigned char **",
        "lineNum": 54,
        "offset": 3,
        "varName": "a1"
    },
    {
        "expr": "v31",
        "exprPointeeSize": 1,
        "exprPointeeType": "unsigned char *",
        "lhsPointeeSize": 1,
        "lhsType": "unsigned char *",
        "lineNum": 55,
        "offset": 0,
        "varName": "v31"
    },
    {
        "expr": "a2[3]",
        "exprPointeeSize": 8,
        "exprPointeeType": "unsigned char *",
        "lhsPointeeSize": 8,
        "lhsType": "unsigned char **",
        "lineNum": 55,
        "offset": 3,
        "varName": "a2"
    },
    {
        "expr": "(_QWORD *)(v26 + 40)",
        "exprPointeeSize": 8,
        "exprPointeeType": "uint64",
        "lhsPointeeSize": 0,
        "lhsType": "long long",
        "lineNum": 58,
        "offset": 40,
        "varName": "v26"
    },
    {
        "expr": "(_QWORD *)(v26 + 32)",
        "exprPointeeSize": 8,
        "exprPointeeType": "uint64",
        "lhsPointeeSize": 0,
        "lhsType": "long long",
        "lineNum": 59,
        "offset": 32,
        "varName": "v26"
    },
    {
        "expr": "v2",
        "exprPointeeSize": 1,
        "exprPointeeType": "unsigned char *",
        "lhsPointeeSize": 1,
        "lhsType": "unsigned char *",
        "lineNum": 60,
        "offset": 0,
        "varName": "v2"
    },
    {
        "expr": "s1",
        "exprPointeeSize": 1,
        "exprPointeeType": "unsigned char *",
        "lhsPointeeSize": 1,
        "lhsType": "unsigned char *",
        "lineNum": 60,
        "offset": 0,
        "varName": "s1"
    },
    {
        "expr": "v29",
        "exprPointeeSize": 1,
        "exprPointeeType": "unsigned char *",
        "lhsPointeeSize": 1,
        "lhsType": "unsigned char *",
        "lineNum": 61,
        "offset": 0,
        "varName": "v29"
    },
    {
        "expr": "s1",
        "exprPointeeSize": 1,
        "exprPointeeType": "unsigned char *",
        "lhsPointeeSize": 1,
        "lhsType": "unsigned char *",
        "lineNum": 61,
        "offset": 0,
        "varName": "s1"
    },
    {
        "expr": "v2",
        "exprPointeeSize": 1,
        "exprPointeeType": "unsigned char *",
        "lhsPointeeSize": 1,
        "lhsType": "unsigned char *",
        "lineNum": 62,
        "offset": 0,
        "varName": "v2"
    },
    {
        "expr": "v29",
        "exprPointeeSize": 1,
        "exprPointeeType": "unsigned char *",
        "lhsPointeeSize": 1,
        "lhsType": "unsigned char *",
        "lineNum": 62,
        "offset": 0,
        "varName": "v29"
    },
    {
        "expr": "v30",
        "exprPointeeSize": 1,
        "exprPointeeType": "unsigned char *",
        "lhsPointeeSize": 1,
        "lhsType": "unsigned char *",
        "lineNum": 63,
        "offset": 0,
        "varName": "v30"
    },
    {
        "expr": "v2",
        "exprPointeeSize": 1,
        "exprPointeeType": "unsigned char *",
        "lhsPointeeSize": 1,
        "lhsType": "unsigned char *",
        "lineNum": 63,
        "offset": 0,
        "varName": "v2"
    },
    {
        "expr": "v3",
        "exprPointeeSize": 1,
        "exprPointeeType": "unsigned char *",
        "lhsPointeeSize": 1,
        "lhsType": "unsigned char *",
        "lineNum": 64,
        "offset": 0,
        "varName": "v3"
    },
    {
        "expr": "s2",
        "exprPointeeSize": 1,
        "exprPointeeType": "unsigned char *",
        "lhsPointeeSize": 1,
        "lhsType": "unsigned char *",
        "lineNum": 64,
        "offset": 0,
        "varName": "s2"
    },
    {
        "expr": "v31",
        "exprPointeeSize": 1,
        "exprPointeeType": "unsigned char *",
        "lhsPointeeSize": 1,
        "lhsType": "unsigned char *",
        "lineNum": 65,
        "offset": 0,
        "varName": "v31"
    },
    {
        "expr": "s2",
        "exprPointeeSize": 1,
        "exprPointeeType": "unsigned char *",
        "lhsPointeeSize": 1,
        "lhsType": "unsigned char *",
        "lineNum": 65,
        "offset": 0,
        "varName": "s2"
    },
    {
        "expr": "v3",
        "exprPointeeSize": 1,
        "exprPointeeType": "unsigned char *",
        "lhsPointeeSize": 1,
        "lhsType": "unsigned char *",
        "lineNum": 66,
        "offset": 0,
        "varName": "v3"
    },
    {
        "expr": "v31",
        "exprPointeeSize": 1,
        "exprPointeeType": "unsigned char *",
        "lhsPointeeSize": 1,
        "lhsType": "unsigned char *",
        "lineNum": 66,
        "offset": 0,
        "varName": "v31"
    },
    {
        "expr": "(_BYTE *)v26",
        "exprPointeeSize": 1,
        "exprPointeeType": "uint8 *",
        "lhsPointeeSize": 1,
        "lhsType": "uint8 *",
        "lineNum": 70,
        "offset": 0,
        "varName": "v26"
    },
    {
        "expr": "(_BYTE *)(v26 + 54)",
        "exprPointeeSize": 1,
        "exprPointeeType": "uint8",
        "lhsPointeeSize": 0,
        "lhsType": "long long",
        "lineNum": 70,
        "offset": 54,
        "varName": "v26"
    },
    {
        "expr": "(_BYTE *)(v26 + 51)",
        "exprPointeeSize": 1,
        "exprPointeeType": "uint8",
        "lhsPointeeSize": 0,
        "lhsType": "long long",
        "lineNum": 70,
        "offset": 51,
        "varName": "v26"
    },
    {
        "expr": "(_BYTE *)(v26 + 56)",
        "exprPointeeSize": 1,
        "exprPointeeType": "uint8",
        "lhsPointeeSize": 0,
        "lhsType": "long long",
        "lineNum": 70,
        "offset": 56,
        "varName": "v26"
    },
    {
        "expr": "ptr",
        "exprPointeeSize": 1,
        "exprPointeeType": "unsigned char *",
        "lhsPointeeSize": 1,
        "lhsType": "unsigned char *",
        "lineNum": 77,
        "offset": 0,
        "varName": "ptr"
    },
    {
        "expr": "v33",
        "exprPointeeSize": 1,
        "exprPointeeType": "unsigned char *",
        "lhsPointeeSize": 1,
        "lhsType": "unsigned char *",
        "lineNum": 78,
        "offset": 0,
        "varName": "v33"
    },
    {
        "expr": "ptr",
        "exprPointeeSize": 1,
        "exprPointeeType": "unsigned char *",
        "lhsPointeeSize": 1,
        "lhsType": "unsigned char *",
        "lineNum": 78,
        "offset": 0,
        "varName": "ptr"
    },
    {
        "expr": "v33",
        "exprPointeeSize": 1,
        "exprPointeeType": "unsigned char *",
        "lhsPointeeSize": 1,
        "lhsType": "unsigned char *",
        "lineNum": 82,
        "offset": 0,
        "varName": "v33"
    },
    {
        "expr": "(unsigned __int8 *)&v45",
        "exprPointeeSize": 1,
        "exprPointeeType": "unsigned char *",
        "lhsPointeeSize": 1,
        "lhsType": "unsigned char *",
        "lineNum": 82,
        "offset": 0,
        "varName": "v45"
    },
    {
        "expr": "ptr",
        "exprPointeeSize": 1,
        "exprPointeeType": "unsigned char *",
        "lhsPointeeSize": 1,
        "lhsType": "unsigned char *",
        "lineNum": 83,
        "offset": 0,
        "varName": "ptr"
    },
    {
        "expr": "v5",
        "exprPointeeSize": 1,
        "exprPointeeType": "unsigned char *",
        "lhsPointeeSize": 1,
        "lhsType": "unsigned char *",
        "lineNum": 98,
        "offset": 0,
        "varName": "v5"
    },
    {
        "expr": "v8",
        "exprPointeeSize": 1,
        "exprPointeeType": "unsigned char *",
        "lhsPointeeSize": 1,
        "lhsType": "unsigned char *",
        "lineNum": 115,
        "offset": 0,
        "varName": "v8"
    },
    {
        "expr": "v33",
        "exprPointeeSize": 1,
        "exprPointeeType": "unsigned char *",
        "lhsPointeeSize": 1,
        "lhsType": "unsigned char *",
        "lineNum": 123,
        "offset": 0,
        "varName": "v33"
    },
    {
        "expr": "s1",
        "exprPointeeSize": 1,
        "exprPointeeType": "unsigned char *",
        "lhsPointeeSize": 1,
        "lhsType": "unsigned char *",
        "lineNum": 123,
        "offset": 0,
        "varName": "s1"
    },
    {
        "expr": "v30",
        "exprPointeeSize": 1,
        "exprPointeeType": "unsigned char *",
        "lhsPointeeSize": 1,
        "lhsType": "unsigned char *",
        "lineNum": 125,
        "offset": 0,
        "varName": "v30"
    },
    {
        "expr": "v30",
        "exprPointeeSize": 1,
        "exprPointeeType": "unsigned char *",
        "lhsPointeeSize": 1,
        "lhsType": "unsigned char *",
        "lineNum": 126,
        "offset": 0,
        "varName": "v30"
    },
    {
        "expr": "v34",
        "exprPointeeSize": 1,
        "exprPointeeType": "unsigned char *",
        "lhsPointeeSize": 1,
        "lhsType": "unsigned char *",
        "lineNum": 127,
        "offset": 0,
        "varName": "v34"
    },
    {
        "expr": "s2",
        "exprPointeeSize": 1,
        "exprPointeeType": "unsigned char *",
        "lhsPointeeSize": 1,
        "lhsType": "unsigned char *",
        "lineNum": 127,
        "offset": 0,
        "varName": "s2"
    },
    {
        "expr": "(_BYTE *)(v26 + 50)",
        "exprPointeeSize": 1,
        "exprPointeeType": "uint8",
        "lhsPointeeSize": 0,
        "lhsType": "long long",
        "lineNum": 132,
        "offset": 50,
        "varName": "v26"
    },
    {
        "expr": "v33",
        "exprPointeeSize": 1,
        "exprPointeeType": "unsigned char *",
        "lhsPointeeSize": 1,
        "lhsType": "unsigned char *",
        "lineNum": 134,
        "offset": 0,
        "varName": "v33"
    },
    {
        "expr": "v34",
        "exprPointeeSize": 1,
        "exprPointeeType": "unsigned char *",
        "lhsPointeeSize": 1,
        "lhsType": "unsigned char *",
        "lineNum": 134,
        "offset": 0,
        "varName": "v34"
    },
    {
        "expr": "(_BYTE *)(v26 + 52)",
        "exprPointeeSize": 1,
        "exprPointeeType": "uint8",
        "lhsPointeeSize": 0,
        "lhsType": "long long",
        "lineNum": 136,
        "offset": 52,
        "varName": "v26"
    },
    {
        "expr": "(const char *)v33",
        "exprPointeeSize": 1,
        "exprPointeeType": "const char *",
        "lhsPointeeSize": 1,
        "lhsType": "const char *",
        "lineNum": 138,
        "offset": 0,
        "varName": "v33"
    },
    {
        "expr": "(const char *)v34",
        "exprPointeeSize": 1,
        "exprPointeeType": "const char *",
        "lhsPointeeSize": 1,
        "lhsType": "const char *",
        "lineNum": 138,
        "offset": 0,
        "varName": "v34"
    },
    {
        "expr": "(_BYTE *)(v26 + 53)",
        "exprPointeeSize": 1,
        "exprPointeeType": "uint8",
        "lhsPointeeSize": 0,
        "lhsType": "long long",
        "lineNum": 140,
        "offset": 53,
        "varName": "v26"
    },
    {
        "expr": "v33",
        "exprPointeeSize": 1,
        "exprPointeeType": "unsigned char *",
        "lhsPointeeSize": 1,
        "lhsType": "unsigned char *",
        "lineNum": 142,
        "offset": 0,
        "varName": "v33"
    },
    {
        "expr": "v34",
        "exprPointeeSize": 1,
        "exprPointeeType": "unsigned char *",
        "lhsPointeeSize": 1,
        "lhsType": "unsigned char *",
        "lineNum": 142,
        "offset": 0,
        "varName": "v34"
    },
    {
        "expr": "(_BYTE *)(v26 + 54)",
        "exprPointeeSize": 1,
        "exprPointeeType": "uint8",
        "lhsPointeeSize": 0,
        "lhsType": "long long",
        "lineNum": 144,
        "offset": 54,
        "varName": "v26"
    },
    {
        "expr": "v33",
        "exprPointeeSize": 1,
        "exprPointeeType": "unsigned char *",
        "lhsPointeeSize": 1,
        "lhsType": "unsigned char *",
        "lineNum": 146,
        "offset": 0,
        "varName": "v33"
    },
    {
        "expr": "v34",
        "exprPointeeSize": 1,
        "exprPointeeType": "unsigned char *",
        "lhsPointeeSize": 1,
        "lhsType": "unsigned char *",
        "lineNum": 147,
        "offset": 0,
        "varName": "v34"
    },
    {
        "expr": "(_BYTE *)(v26 + 51)",
        "exprPointeeSize": 1,
        "exprPointeeType": "uint8",
        "lhsPointeeSize": 0,
        "lhsType": "long long",
        "lineNum": 149,
        "offset": 51,
        "varName": "v26"
    },
    {
        "expr": "(_BYTE *)(v26 + 56)",
        "exprPointeeSize": 1,
        "exprPointeeType": "uint8",
        "lhsPointeeSize": 0,
        "lhsType": "long long",
        "lineNum": 153,
        "offset": 56,
        "varName": "v26"
    },
    {
        "expr": "v33",
        "exprPointeeSize": 1,
        "exprPointeeType": "unsigned char *",
        "lhsPointeeSize": 1,
        "lhsType": "unsigned char *",
        "lineNum": 155,
        "offset": 0,
        "varName": "v33"
    },
    {
        "expr": "v34",
        "exprPointeeSize": 1,
        "exprPointeeType": "unsigned char *",
        "lhsPointeeSize": 1,
        "lhsType": "unsigned char *",
        "lineNum": 155,
        "offset": 0,
        "varName": "v34"
    },
    {
        "expr": "ptr",
        "exprPointeeSize": 1,
        "exprPointeeType": "unsigned char *",
        "lhsPointeeSize": 1,
        "lhsType": "unsigned char *",
        "lineNum": 170,
        "offset": 0,
        "varName": "ptr"
    },
    {
        "expr": "s1",
        "exprPointeeSize": 1,
        "exprPointeeType": "unsigned char *",
        "lhsPointeeSize": 1,
        "lhsType": "unsigned char *",
        "lineNum": 185,
        "offset": 0,
        "varName": "s1"
    },
    {
        "expr": "v30",
        "exprPointeeSize": 1,
        "exprPointeeType": "unsigned char *",
        "lhsPointeeSize": 1,
        "lhsType": "unsigned char *",
        "lineNum": 185,
        "offset": 0,
        "varName": "v30"
    },
    {
        "expr": "s1",
        "exprPointeeSize": 1,
        "exprPointeeType": "unsigned char *",
        "lhsPointeeSize": 1,
        "lhsType": "unsigned char *",
        "lineNum": 185,
        "offset": 0,
        "varName": "s1"
    },
    {
        "expr": "s1",
        "exprPointeeSize": 1,
        "exprPointeeType": "unsigned char *",
        "lhsPointeeSize": 1,
        "lhsType": "unsigned char *",
        "lineNum": 186,
        "offset": 0,
        "varName": "s1"
    },
    {
        "expr": "s2",
        "exprPointeeSize": 1,
        "exprPointeeType": "unsigned char *",
        "lhsPointeeSize": 1,
        "lhsType": "unsigned char *",
        "lineNum": 187,
        "offset": 0,
        "varName": "s2"
    },
    {
        "expr": "s2",
        "exprPointeeSize": 1,
        "exprPointeeType": "unsigned char *",
        "lhsPointeeSize": 1,
        "lhsType": "unsigned char *",
        "lineNum": 188,
        "offset": 0,
        "varName": "s2"
    },
    {
        "expr": "s1",
        "exprPointeeSize": 1,
        "exprPointeeType": "unsigned char *",
        "lhsPointeeSize": 1,
        "lhsType": "unsigned char *",
        "lineNum": 189,
        "offset": 0,
        "varName": "s1"
    },
    {
        "expr": "v30",
        "exprPointeeSize": 1,
        "exprPointeeType": "unsigned char *",
        "lhsPointeeSize": 1,
        "lhsType": "unsigned char *",
        "lineNum": 189,
        "offset": 0,
        "varName": "v30"
    },
    {
        "expr": "s1",
        "exprPointeeSize": 1,
        "exprPointeeType": "unsigned char *",
        "lhsPointeeSize": 1,
        "lhsType": "unsigned char *",
        "lineNum": 191,
        "offset": 0,
        "varName": "s1"
    },
    {
        "expr": "s2",
        "exprPointeeSize": 1,
        "exprPointeeType": "unsigned char *",
        "lhsPointeeSize": 1,
        "lhsType": "unsigned char *",
        "lineNum": 193,
        "offset": 0,
        "varName": "s2"
    },
    {
        "expr": "s1",
        "exprPointeeSize": 1,
        "exprPointeeType": "unsigned char *",
        "lhsPointeeSize": 1,
        "lhsType": "unsigned char *",
        "lineNum": 197,
        "offset": 0,
        "varName": "s1"
    },
    {
        "expr": "s2",
        "exprPointeeSize": 1,
        "exprPointeeType": "unsigned char *",
        "lhsPointeeSize": 1,
        "lhsType": "unsigned char *",
        "lineNum": 198,
        "offset": 0,
        "varName": "s2"
    },
    {
        "expr": "s1",
        "exprPointeeSize": 1,
        "exprPointeeType": "unsigned char *",
        "lhsPointeeSize": 1,
        "lhsType": "unsigned char *",
        "lineNum": 200,
        "offset": 0,
        "varName": "s1"
    },
    {
        "expr": "v30",
        "exprPointeeSize": 1,
        "exprPointeeType": "unsigned char *",
        "lhsPointeeSize": 1,
        "lhsType": "unsigned char *",
        "lineNum": 200,
        "offset": 0,
        "varName": "v30"
    },
    {
        "expr": "s1",
        "exprPointeeSize": 1,
        "exprPointeeType": "unsigned char *",
        "lhsPointeeSize": 1,
        "lhsType": "unsigned char *",
        "lineNum": 206,
        "offset": 0,
        "varName": "s1"
    },
    {
        "expr": "v30",
        "exprPointeeSize": 1,
        "exprPointeeType": "unsigned char *",
        "lhsPointeeSize": 1,
        "lhsType": "unsigned char *",
        "lineNum": 206,
        "offset": 0,
        "varName": "v30"
    },
    {
        "expr": "s1",
        "exprPointeeSize": 1,
        "exprPointeeType": "unsigned char *",
        "lhsPointeeSize": 1,
        "lhsType": "unsigned char *",
        "lineNum": 206,
        "offset": 0,
        "varName": "s1"
    },
    {
        "expr": "s1",
        "exprPointeeSize": 1,
        "exprPointeeType": "unsigned char *",
        "lhsPointeeSize": 1,
        "lhsType": "unsigned char *",
        "lineNum": 207,
        "offset": 0,
        "varName": "s1"
    },
    {
        "expr": "s2",
        "exprPointeeSize": 1,
        "exprPointeeType": "unsigned char *",
        "lhsPointeeSize": 1,
        "lhsType": "unsigned char *",
        "lineNum": 208,
        "offset": 0,
        "varName": "s2"
    },
    {
        "expr": "s2",
        "exprPointeeSize": 1,
        "exprPointeeType": "unsigned char *",
        "lhsPointeeSize": 1,
        "lhsType": "unsigned char *",
        "lineNum": 209,
        "offset": 0,
        "varName": "s2"
    },
    {
        "expr": "s1",
        "exprPointeeSize": 1,
        "exprPointeeType": "unsigned char *",
        "lhsPointeeSize": 1,
        "lhsType": "unsigned char *",
        "lineNum": 210,
        "offset": 0,
        "varName": "s1"
    },
    {
        "expr": "v30",
        "exprPointeeSize": 1,
        "exprPointeeType": "unsigned char *",
        "lhsPointeeSize": 1,
        "lhsType": "unsigned char *",
        "lineNum": 210,
        "offset": 0,
        "varName": "v30"
    },
    {
        "expr": "s1",
        "exprPointeeSize": 1,
        "exprPointeeType": "unsigned char *",
        "lhsPointeeSize": 1,
        "lhsType": "unsigned char *",
        "lineNum": 212,
        "offset": 0,
        "varName": "s1"
    },
    {
        "expr": "s2",
        "exprPointeeSize": 1,
        "exprPointeeType": "unsigned char *",
        "lhsPointeeSize": 1,
        "lhsType": "unsigned char *",
        "lineNum": 213,
        "offset": 0,
        "varName": "s2"
    },
    {
        "expr": "s1",
        "exprPointeeSize": 1,
        "exprPointeeType": "unsigned char *",
        "lhsPointeeSize": 1,
        "lhsType": "unsigned char *",
        "lineNum": 216,
        "offset": 0,
        "varName": "s1"
    },
    {
        "expr": "s2",
        "exprPointeeSize": 1,
        "exprPointeeType": "unsigned char *",
        "lhsPointeeSize": 1,
        "lhsType": "unsigned char *",
        "lineNum": 217,
        "offset": 0,
        "varName": "s2"
    },
    {
        "expr": "s1",
        "exprPointeeSize": 1,
        "exprPointeeType": "unsigned char *",
        "lhsPointeeSize": 1,
        "lhsType": "unsigned char *",
        "lineNum": 219,
        "offset": 0,
        "varName": "s1"
    },
    {
        "expr": "v30",
        "exprPointeeSize": 1,
        "exprPointeeType": "unsigned char *",
        "lhsPointeeSize": 1,
        "lhsType": "unsigned char *",
        "lineNum": 219,
        "offset": 0,
        "varName": "v30"
    },
    {
        "expr": "s1",
        "exprPointeeSize": 1,
        "exprPointeeType": "unsigned char *",
        "lhsPointeeSize": 1,
        "lhsType": "unsigned char *",
        "lineNum": 232,
        "offset": 0,
        "varName": "s1"
    },
    {
        "expr": "v30",
        "exprPointeeSize": 1,
        "exprPointeeType": "unsigned char *",
        "lhsPointeeSize": 1,
        "lhsType": "unsigned char *",
        "lineNum": 232,
        "offset": 0,
        "varName": "v30"
    },
    {
        "expr": "v15",
        "exprPointeeSize": 1,
        "exprPointeeType": "unsigned char *",
        "lhsPointeeSize": 1,
        "lhsType": "unsigned char *",
        "lineNum": 234,
        "offset": 0,
        "varName": "v15"
    },
    {
        "expr": "s1",
        "exprPointeeSize": 1,
        "exprPointeeType": "unsigned char *",
        "lhsPointeeSize": 1,
        "lhsType": "unsigned char *",
        "lineNum": 234,
        "offset": 0,
        "varName": "s1"
    },
    {
        "expr": "v15",
        "exprPointeeSize": 1,
        "exprPointeeType": "unsigned char *",
        "lhsPointeeSize": 1,
        "lhsType": "unsigned char *",
        "lineNum": 235,
        "offset": 0,
        "varName": "v15"
    },
    {
        "expr": "v18",
        "exprPointeeSize": 1,
        "exprPointeeType": "unsigned char *",
        "lhsPointeeSize": 1,
        "lhsType": "unsigned char *",
        "lineNum": 237,
        "offset": 0,
        "varName": "v18"
    },
    {
        "expr": "s2",
        "exprPointeeSize": 1,
        "exprPointeeType": "unsigned char *",
        "lhsPointeeSize": 1,
        "lhsType": "unsigned char *",
        "lineNum": 237,
        "offset": 0,
        "varName": "s2"
    },
    {
        "expr": "v18",
        "exprPointeeSize": 1,
        "exprPointeeType": "unsigned char *",
        "lhsPointeeSize": 1,
        "lhsType": "unsigned char *",
        "lineNum": 238,
        "offset": 0,
        "varName": "v18"
    },
    {
        "expr": "(_QWORD *)(v26 + 64)",
        "exprPointeeSize": 8,
        "exprPointeeType": "uint64",
        "lhsPointeeSize": 0,
        "lhsType": "long long",
        "lineNum": 261,
        "offset": 64,
        "varName": "v26"
    },
    {
        "expr": "(_QWORD *)(v26 + 16)",
        "exprPointeeSize": 8,
        "exprPointeeType": "uint64",
        "lhsPointeeSize": 0,
        "lhsType": "long long",
        "lineNum": 264,
        "offset": 16,
        "varName": "v26"
    },
    {
        "expr": "v29",
        "exprPointeeSize": 1,
        "exprPointeeType": "unsigned char *",
        "lhsPointeeSize": 1,
        "lhsType": "unsigned char *",
        "lineNum": 266,
        "offset": 0,
        "varName": "v29"
    },
    {
        "expr": "a1[1]",
        "exprPointeeSize": 8,
        "exprPointeeType": "unsigned char *",
        "lhsPointeeSize": 8,
        "lhsType": "unsigned char **",
        "lineNum": 266,
        "offset": 1,
        "varName": "a1"
    },
    {
        "expr": "a1",
        "exprPointeeSize": 8,
        "exprPointeeType": "unsigned char **",
        "lhsPointeeSize": 8,
        "lhsType": "unsigned char **",
        "lineNum": 266,
        "offset": 0,
        "varName": "a1"
    },
    {
        "expr": "v31",
        "exprPointeeSize": 1,
        "exprPointeeType": "unsigned char *",
        "lhsPointeeSize": 1,
        "lhsType": "unsigned char *",
        "lineNum": 267,
        "offset": 0,
        "varName": "v31"
    },
    {
        "expr": "a2[1]",
        "exprPointeeSize": 8,
        "exprPointeeType": "unsigned char *",
        "lhsPointeeSize": 8,
        "lhsType": "unsigned char **",
        "lineNum": 267,
        "offset": 1,
        "varName": "a2"
    },
    {
        "expr": "a2",
        "exprPointeeSize": 8,
        "exprPointeeType": "unsigned char **",
        "lhsPointeeSize": 8,
        "lhsType": "unsigned char **",
        "lineNum": 267,
        "offset": 0,
        "varName": "a2"
    },
    {
        "expr": "v29",
        "exprPointeeSize": 1,
        "exprPointeeType": "unsigned char *",
        "lhsPointeeSize": 1,
        "lhsType": "unsigned char *",
        "lineNum": 271,
        "offset": 0,
        "varName": "v29"
    },
    {
        "expr": "v31",
        "exprPointeeSize": 1,
        "exprPointeeType": "unsigned char *",
        "lhsPointeeSize": 1,
        "lhsType": "unsigned char *",
        "lineNum": 272,
        "offset": 0,
        "varName": "v31"
    },
    {
        "expr": "(_QWORD *)v26",
        "exprPointeeSize": 8,
        "exprPointeeType": "uint64 *",
        "lhsPointeeSize": 8,
        "lhsType": "uint64 *",
        "lineNum": 274,
        "offset": 0,
        "varName": "v26"
    },
    {
        "expr": "s1",
        "exprPointeeSize": 1,
        "exprPointeeType": "unsigned char *",
        "lhsPointeeSize": 1,
        "lhsType": "unsigned char *",
        "lineNum": 276,
        "offset": 0,
        "varName": "s1"
    },
    {
        "expr": "a1",
        "exprPointeeSize": 8,
        "exprPointeeType": "unsigned char **",
        "lhsPointeeSize": 8,
        "lhsType": "unsigned char **",
        "lineNum": 276,
        "offset": 0,
        "varName": "a1"
    },
    {
        "expr": "s2",
        "exprPointeeSize": 1,
        "exprPointeeType": "unsigned char *",
        "lhsPointeeSize": 1,
        "lhsType": "unsigned char *",
        "lineNum": 277,
        "offset": 0,
        "varName": "s2"
    },
    {
        "expr": "a2",
        "exprPointeeSize": 8,
        "exprPointeeType": "unsigned char **",
        "lhsPointeeSize": 8,
        "lhsType": "unsigned char **",
        "lineNum": 277,
        "offset": 0,
        "varName": "a2"
    },
    {
        "expr": "(_BYTE *)(v26 + 48)",
        "exprPointeeSize": 1,
        "exprPointeeType": "uint8",
        "lhsPointeeSize": 0,
        "lhsType": "long long",
        "lineNum": 278,
        "offset": 48,
        "varName": "v26"
    },
    {
        "expr": "s1",
        "exprPointeeSize": 1,
        "exprPointeeType": "unsigned char *",
        "lhsPointeeSize": 1,
        "lhsType": "unsigned char *",
        "lineNum": 288,
        "offset": 0,
        "varName": "s1"
    },
    {
        "expr": "(__int64 *)v26",
        "exprPointeeSize": 8,
        "exprPointeeType": "long long *",
        "lhsPointeeSize": 8,
        "lhsType": "long long *",
        "lineNum": 288,
        "offset": 0,
        "varName": "v26"
    },
    {
        "expr": "s2",
        "exprPointeeSize": 1,
        "exprPointeeType": "unsigned char *",
        "lhsPointeeSize": 1,
        "lhsType": "unsigned char *",
        "lineNum": 289,
        "offset": 0,
        "varName": "s2"
    },
    {
        "expr": "(__int64 *)v26",
        "exprPointeeSize": 8,
        "exprPointeeType": "long long *",
        "lhsPointeeSize": 8,
        "lhsType": "long long *",
        "lineNum": 289,
        "offset": 0,
        "varName": "v26"
    },
    {
        "expr": "(_BYTE *)(v26 + 55)",
        "exprPointeeSize": 1,
        "exprPointeeType": "uint8",
        "lhsPointeeSize": 0,
        "lhsType": "long long",
        "lineNum": 294,
        "offset": 55,
        "varName": "v26"
    }
]