[
    {
        "args": [
            "*a1"
        ],
        "funName": "sub_40153D",
        "lineNum": 22
    },
    {
        "args": [
            "v11"
        ],
        "funName": "sub_401773",
        "lineNum": 25
    },
    {
        "args": [
            "a1"
        ],
        "funName": "sub_402474",
        "lineNum": 32
    },
    {
        "args": [
            "ptr"
        ],
        "funName": "sub_402474",
        "lineNum": 57
    },
    {
        "args": [
            "v11"
        ],
        "funName": "sub_401773",
        "lineNum": 71
    }
]