{
    "argument": [
        {
            "name": "a1",
            "type": "__int64",
            "original_line": "__int64 a1"
        },
        {
            "name": "a2",
            "type": "_QWORD *",
            "original_line": "_QWORD *a2"
        },
        {
            "name": "a3",
            "type": "_DWORD *",
            "original_line": "_DWORD *a3"
        },
        {
            "name": "a4",
            "type": "_DWORD *",
            "original_line": "_DWORD *a4"
        },
        {
            "name": "a5",
            "type": "int *",
            "original_line": "int *a5"
        },
        {
            "name": "a6",
            "type": "_DWORD *",
            "original_line": "_DWORD *a6"
        },
        {
            "name": "a7",
            "type": "_DWORD *",
            "original_line": "_DWORD *a7"
        }
    ],
    "variable": [
        {
            "name": "v7",
            "type": "int",
            "comment": "eax",
            "array_size": null,
            "star_count": 0,
            "rbp_offset_hex": null,
            "rbp_offset_dec": null,
            "original_line": "int v7; // eax"
        },
        {
            "name": "v8",
            "type": "__int64",
            "comment": "rbx",
            "array_size": null,
            "star_count": 0,
            "rbp_offset_hex": null,
            "rbp_offset_dec": null,
            "original_line": "__int64 v8; // rbx"
        },
        {
            "name": "v9",
            "type": "char *",
            "comment": "rax",
            "array_size": null,
            "star_count": 0,
            "rbp_offset_hex": null,
            "rbp_offset_dec": null,
            "original_line": "char *v9; // rax"
        },
        {
            "name": "v10",
            "type": "__int64",
            "comment": "rax",
            "array_size": null,
            "star_count": 0,
            "rbp_offset_hex": null,
            "rbp_offset_dec": null,
            "original_line": "__int64 v10; // rax"
        },
        {
            "name": "v11",
            "type": "__int64",
            "comment": "rax",
            "array_size": null,
            "star_count": 0,
            "rbp_offset_hex": null,
            "rbp_offset_dec": null,
            "original_line": "__int64 v11; // rax"
        },
        {
            "name": "result",
            "type": "unsigned __int64",
            "comment": "rax",
            "array_size": null,
            "star_count": 0,
            "rbp_offset_hex": null,
            "rbp_offset_dec": null,
            "original_line": "unsigned __int64 result; // rax"
        },
        {
            "name": "v16",
            "type": "bool",
            "comment": "[rsp+33h] [rbp-1Dh]",
            "array_size": null,
            "star_count": 0,
            "rbp_offset_hex": "-1D",
            "rbp_offset_dec": -29,
            "original_line": "bool v16; // [rsp+33h] [rbp-1Dh]"
        },
        {
            "name": "v17",
            "type": "int",
            "comment": "[rsp+34h] [rbp-1Ch]",
            "array_size": null,
            "star_count": 0,
            "rbp_offset_hex": "-1C",
            "rbp_offset_dec": -28,
            "original_line": "int v17; // [rsp+34h] [rbp-1Ch]"
        },
        {
            "name": "v18",
            "type": "char *",
            "comment": "[rsp+38h] [rbp-18h]",
            "array_size": null,
            "star_count": 0,
            "rbp_offset_hex": "-18",
            "rbp_offset_dec": -24,
            "original_line": "char *v18; // [rsp+38h] [rbp-18h]"
        }
    ]
}