[
    {
        "expr": "v140",
        "exprPointeeSize": 4,
        "exprPointeeType": "int *",
        "lhsPointeeSize": 4,
        "lhsType": "int *",
        "lineNum": 160,
        "offset": 0,
        "varName": "v140"
    },
    {
        "expr": "a1",
        "exprPointeeSize": 4,
        "exprPointeeType": "int *",
        "lhsPointeeSize": 4,
        "lhsType": "int *",
        "lineNum": 160,
        "offset": 0,
        "varName": "a1"
    },
    {
        "expr": "a3",
        "exprPointeeSize": 4,
        "exprPointeeType": "uint32 *",
        "lhsPointeeSize": 4,
        "lhsType": "uint32 *",
        "lineNum": 161,
        "offset": 0,
        "varName": "a3"
    },
    {
        "expr": "a3[1]",
        "exprPointeeSize": 4,
        "exprPointeeType": "uint32",
        "lhsPointeeSize": 4,
        "lhsType": "uint32 *",
        "lineNum": 162,
        "offset": 1,
        "varName": "a3"
    },
    {
        "expr": "a3[2]",
        "exprPointeeSize": 4,
        "exprPointeeType": "uint32",
        "lhsPointeeSize": 4,
        "lhsType": "uint32 *",
        "lineNum": 163,
        "offset": 2,
        "varName": "a3"
    },
    {
        "expr": "a3[3]",
        "exprPointeeSize": 4,
        "exprPointeeType": "uint32",
        "lhsPointeeSize": 4,
        "lhsType": "uint32 *",
        "lineNum": 164,
        "offset": 3,
        "varName": "a3"
    },
    {
        "expr": "a3[4]",
        "exprPointeeSize": 4,
        "exprPointeeType": "uint32",
        "lhsPointeeSize": 4,
        "lhsType": "uint32 *",
        "lineNum": 165,
        "offset": 4,
        "varName": "a3"
    },
    {
        "expr": "a3[4]",
        "exprPointeeSize": 4,
        "exprPointeeType": "uint32",
        "lhsPointeeSize": 4,
        "lhsType": "uint32 *",
        "lineNum": 166,
        "offset": 4,
        "varName": "a3"
    },
    {
        "expr": "a3[5]",
        "exprPointeeSize": 4,
        "exprPointeeType": "uint32",
        "lhsPointeeSize": 4,
        "lhsType": "uint32 *",
        "lineNum": 167,
        "offset": 5,
        "varName": "a3"
    },
    {
        "expr": "v140",
        "exprPointeeSize": 4,
        "exprPointeeType": "int *",
        "lhsPointeeSize": 4,
        "lhsType": "int *",
        "lineNum": 168,
        "offset": 0,
        "varName": "v140"
    },
    {
        "expr": "v140",
        "exprPointeeSize": 4,
        "exprPointeeType": "int *",
        "lhsPointeeSize": 4,
        "lhsType": "int *",
        "lineNum": 174,
        "offset": 0,
        "varName": "v140"
    },
    {
        "expr": "v140",
        "exprPointeeSize": 4,
        "exprPointeeType": "int *",
        "lhsPointeeSize": 4,
        "lhsType": "int *",
        "lineNum": 175,
        "offset": 0,
        "varName": "v140"
    },
    {
        "expr": "v141",
        "exprPointeeSize": 4,
        "exprPointeeType": "int *",
        "lhsPointeeSize": 4,
        "lhsType": "int *",
        "lineNum": 176,
        "offset": 0,
        "varName": "v141"
    },
    {
        "expr": "v140 + 1",
        "exprPointeeSize": 4,
        "exprPointeeType": "int",
        "lhsPointeeSize": 4,
        "lhsType": "int *",
        "lineNum": 176,
        "offset": 1,
        "varName": "v140"
    },
    {
        "expr": "v141",
        "exprPointeeSize": 4,
        "exprPointeeType": "int *",
        "lhsPointeeSize": 4,
        "lhsType": "int *",
        "lineNum": 179,
        "offset": 0,
        "varName": "v141"
    },
    {
        "expr": "v141",
        "exprPointeeSize": 4,
        "exprPointeeType": "int *",
        "lhsPointeeSize": 4,
        "lhsType": "int *",
        "lineNum": 182,
        "offset": 0,
        "varName": "v141"
    },
    {
        "expr": "v141",
        "exprPointeeSize": 4,
        "exprPointeeType": "int *",
        "lhsPointeeSize": 4,
        "lhsType": "int *",
        "lineNum": 185,
        "offset": 0,
        "varName": "v141"
    },
    {
        "expr": "v141",
        "exprPointeeSize": 4,
        "exprPointeeType": "int *",
        "lhsPointeeSize": 4,
        "lhsType": "int *",
        "lineNum": 188,
        "offset": 0,
        "varName": "v141"
    },
    {
        "expr": "v141",
        "exprPointeeSize": 4,
        "exprPointeeType": "int *",
        "lhsPointeeSize": 4,
        "lhsType": "int *",
        "lineNum": 191,
        "offset": 0,
        "varName": "v141"
    },
    {
        "expr": "v141",
        "exprPointeeSize": 4,
        "exprPointeeType": "int *",
        "lhsPointeeSize": 4,
        "lhsType": "int *",
        "lineNum": 194,
        "offset": 0,
        "varName": "v141"
    },
    {
        "expr": "v141",
        "exprPointeeSize": 4,
        "exprPointeeType": "int *",
        "lhsPointeeSize": 4,
        "lhsType": "int *",
        "lineNum": 197,
        "offset": 0,
        "varName": "v141"
    },
    {
        "expr": "v141",
        "exprPointeeSize": 4,
        "exprPointeeType": "int *",
        "lhsPointeeSize": 4,
        "lhsType": "int *",
        "lineNum": 200,
        "offset": 0,
        "varName": "v141"
    },
    {
        "expr": "v141",
        "exprPointeeSize": 4,
        "exprPointeeType": "int *",
        "lhsPointeeSize": 4,
        "lhsType": "int *",
        "lineNum": 203,
        "offset": 0,
        "varName": "v141"
    },
    {
        "expr": "v141",
        "exprPointeeSize": 4,
        "exprPointeeType": "int *",
        "lhsPointeeSize": 4,
        "lhsType": "int *",
        "lineNum": 206,
        "offset": 0,
        "varName": "v141"
    },
    {
        "expr": "v141",
        "exprPointeeSize": 4,
        "exprPointeeType": "int *",
        "lhsPointeeSize": 4,
        "lhsType": "int *",
        "lineNum": 209,
        "offset": 0,
        "varName": "v141"
    },
    {
        "expr": "v141",
        "exprPointeeSize": 4,
        "exprPointeeType": "int *",
        "lhsPointeeSize": 4,
        "lhsType": "int *",
        "lineNum": 212,
        "offset": 0,
        "varName": "v141"
    },
    {
        "expr": "v141",
        "exprPointeeSize": 4,
        "exprPointeeType": "int *",
        "lhsPointeeSize": 4,
        "lhsType": "int *",
        "lineNum": 215,
        "offset": 0,
        "varName": "v141"
    },
    {
        "expr": "v141",
        "exprPointeeSize": 4,
        "exprPointeeType": "int *",
        "lhsPointeeSize": 4,
        "lhsType": "int *",
        "lineNum": 218,
        "offset": 0,
        "varName": "v141"
    },
    {
        "expr": "v141",
        "exprPointeeSize": 4,
        "exprPointeeType": "int *",
        "lhsPointeeSize": 4,
        "lhsType": "int *",
        "lineNum": 221,
        "offset": 0,
        "varName": "v141"
    },
    {
        "expr": "v140",
        "exprPointeeSize": 4,
        "exprPointeeType": "int *",
        "lhsPointeeSize": 4,
        "lhsType": "int *",
        "lineNum": 222,
        "offset": 0,
        "varName": "v140"
    },
    {
        "expr": "v141 + 1",
        "exprPointeeSize": 4,
        "exprPointeeType": "int",
        "lhsPointeeSize": 4,
        "lhsType": "int *",
        "lineNum": 222,
        "offset": 1,
        "varName": "v141"
    },
    {
        "expr": "a3",
        "exprPointeeSize": 4,
        "exprPointeeType": "uint32 *",
        "lhsPointeeSize": 4,
        "lhsType": "uint32 *",
        "lineNum": 325,
        "offset": 0,
        "varName": "a3"
    },
    {
        "expr": "a3[1]",
        "exprPointeeSize": 4,
        "exprPointeeType": "uint32",
        "lhsPointeeSize": 4,
        "lhsType": "uint32 *",
        "lineNum": 326,
        "offset": 1,
        "varName": "a3"
    },
    {
        "expr": "a3[2]",
        "exprPointeeSize": 4,
        "exprPointeeType": "uint32",
        "lhsPointeeSize": 4,
        "lhsType": "uint32 *",
        "lineNum": 327,
        "offset": 2,
        "varName": "a3"
    },
    {
        "expr": "result",
        "exprPointeeSize": 4,
        "exprPointeeType": "uint32 *",
        "lhsPointeeSize": 4,
        "lhsType": "uint32 *",
        "lineNum": 328,
        "offset": 0,
        "varName": "result"
    },
    {
        "expr": "a3",
        "exprPointeeSize": 4,
        "exprPointeeType": "uint32 *",
        "lhsPointeeSize": 4,
        "lhsType": "uint32 *",
        "lineNum": 328,
        "offset": 0,
        "varName": "a3"
    },
    {
        "expr": "a3[3]",
        "exprPointeeSize": 4,
        "exprPointeeType": "uint32",
        "lhsPointeeSize": 4,
        "lhsType": "uint32 *",
        "lineNum": 329,
        "offset": 3,
        "varName": "a3"
    },
    {
        "expr": "result",
        "exprPointeeSize": 4,
        "exprPointeeType": "uint32 *",
        "lhsPointeeSize": 4,
        "lhsType": "uint32 *",
        "lineNum": 330,
        "offset": 0,
        "varName": "result"
    }
]