{
    "argument": [
        {
            "name": "a1",
            "type": "const struct timespec *",
            "original_line": "const struct timespec *a1"
        }
    ],
    "variable": [
        {
            "name": "v2",
            "type": "int",
            "comment": "[rsp+1Ch] [rbp-14h]",
            "array_size": null,
            "star_count": 0,
            "rbp_offset_hex": "-14",
            "rbp_offset_dec": -20,
            "original_line": "int v2; // [rsp+1Ch] [rbp-14h]"
        },
        {
            "name": "tv",
            "type": "struct timeval",
            "comment": "[rsp+20h] [rbp-10h] BYREF",
            "array_size": null,
            "star_count": 0,
            "rbp_offset_hex": "-10",
            "rbp_offset_dec": -16,
            "original_line": "struct timeval tv; // [rsp+20h] [rbp-10h] BYREF"
        }
    ]
}